namednumber/__init__.py
namednumber/__main__.py
namednumber/fancy_number.py
namednumber/name_fmt.py
namednumber/named_number.py
namednumber/options.py
namednumber/wordlists/128_plural_animals.txt
namednumber/wordlists/128_singular_animals.txt
namednumber/wordlists/1k_adjectives.txt
namednumber/wordlists/1k_plural_nouns.txt
namednumber/wordlists/1k_singular_nouns.txt
namednumber-1.0.0.dist-info/LICENSE
namednumber-1.0.0.dist-info/METADATA
namednumber-1.0.0.dist-info/WHEEL
namednumber-1.0.0.dist-info/entry_points.txt
namednumber-1.0.0.dist-info/top_level.txt
namednumber-1.0.0.dist-info/RECORD
