Metadata-Version: 2.1
Name: namednumber
Version: 1.0.0
Summary: Map integers to fun pseudo-random names following a custom format
Author-email: Torin Halsted <modularizer@gmail.com>
License: MIT License        
Project-URL: Homepage, https://modularizer.github.io/namednumber/
Keywords: password-generator,number-to-words,name,uuid-generator
Classifier: License :: OSI Approved :: MIT License
Classifier: Programming Language :: Python
Classifier: Programming Language :: Python :: 3
Classifier: Programming Language :: Python :: 3.10
Requires-Python: >=3.10
License-File: LICENSE
Requires-Dist: numpy
Provides-Extra: dev
Requires-Dist: pyyaml ; extra == 'dev'
Requires-Dist: pip-tools ; extra == 'dev'
Requires-Dist: pytest ; extra == 'dev'
